meta_prn/__init__.py
meta_prn/action_items.py
meta_prn/admin_site.py
meta_prn/apps.py
meta_prn/choices.py
meta_prn/constants.py
meta_prn/urls.py
meta_prn/views.py
meta_prn/admin/__init__.py
meta_prn/admin/autocomplete_admin.py
meta_prn/admin/end_of_study_admin.py
meta_prn/admin/onschedule_admin.py
meta_prn/admin/protocol_deviation_violation_admin.py
meta_prn/admin/unblinding_request_admin.py
meta_prn/admin/unblinding_review_admin.py
meta_prn/form_validators/__init__.py
meta_prn/form_validators/death_report.py
meta_prn/form_validators/end_of_study.py
meta_prn/form_validators/protocol_deviation_violation.py
meta_prn/form_validators/study_day_form_validator_mixin.py
meta_prn/form_validators/validate_death_report_mixin.py
meta_prn/forms/__init__.py
meta_prn/forms/end_of_study_form.py
meta_prn/forms/loss_to_followup.py
meta_prn/forms/protocol_deviation_violation_form.py
meta_prn/forms/unblinding_request_form.py
meta_prn/forms/unblinding_review_form.py
meta_prn/migrations/0001_initial.py
meta_prn/migrations/0002_auto_20191024_1000.py
meta_prn/migrations/0003_auto_20200120_2020.py
meta_prn/migrations/__init__.py
meta_prn/models/__init__.py
meta_prn/models/base_study_termination.py
meta_prn/models/end_of_study.py
meta_prn/models/loss_to_followup.py
meta_prn/models/onschedule.py
meta_prn/models/protocol_deviation_violation.py
meta_prn/models/unblinding_request.py
meta_prn/models/unblinding_review.py
meta_prn/models/unblinding_user.py
meta_prn/tests/__init__.py
meta_prn/tests/urls.py
meta_prn/tests/tests/__init__.py
meta_prn-0.1.14.dist-info/AUTHORS
meta_prn-0.1.14.dist-info/LICENSE
meta_prn-0.1.14.dist-info/METADATA
meta_prn-0.1.14.dist-info/WHEEL
meta_prn-0.1.14.dist-info/top_level.txt
meta_prn-0.1.14.dist-info/RECORD
